Metadata-Version: 2.1
Name: optimodel
Version: 0.2.1
Summary: Tools for generating ~shortest MILP and SAT models
Author-email: Aleksei Udovenko <aleksei@affine.group>
License: MIT License
Project-URL: Repository, https://github.com/hellman/optimodel
Keywords: minimization,linear-programming,milp,cnf,dnf,satisfiability,bitvectors
Requires-Python: >=3.7
License-File: LICENSE
Requires-Dist: binteger
Requires-Dist: subsets
Requires-Dist: optisolveapi
Requires-Dist: monolearn
Requires-Dist: justlogs
Provides-Extra: glpk
Requires-Dist: optisolveapi[glpk]; extra == "glpk"
Provides-Extra: pysat
Requires-Dist: optisolveapi[pysat]; extra == "pysat"
Provides-Extra: scip
Requires-Dist: optisolveapi[scip]; extra == "scip"
Provides-Extra: gurobi
Requires-Dist: optisolveapi[gurobi]; extra == "gurobi"
